Workbook

Sheet Start Here
A1: Savings Comparison: Start Here
A2: 1. On 'My Inputs', fill in the yellow cells: how much you can save each month, your down payment goal, and how many years to project.
A3: 2. On 'Bank Products', the rates and fees are illustrative values made for this project. Check each bank's website for current figures before relying on them.
A4: 3. Look at 'Dashboard' for the balance each option reaches, what it cost you in fees, and how long it takes to reach your goal.
A6: Colour key: yellow cells with blue text are things you type. Everything else is a formula, so don't type over it.
A7: Assumptions: contributions are added once a year and returns compound yearly. This is a simple approximation, not bank advice.
A8: All rates and fees in this workbook are illustrative. They were made up for this project to show how the model works. They are not real bank offers.
A10: Stuck on a term? See the Glossary tab for plain-English definitions of GICs, MERs, TFSAs and more.
A11: Please read the Disclaimers tab before relying on any result.

Sheet Disclaimers
A1: Disclaimers
A2: Please read this before relying on any result in this workbook. Last reviewed: October 2026.
A4: What this tool is
A5: • A planning tool that shows how savings, fees, and time can affect a balance. It is for learning and rough comparisons, not for deciding where to put your money.
A6: • It does not recommend any bank, product, or strategy.
A8: Illustrative numbers
A9: • The rates and fund fees in this file are illustrative values made for this project, to show how the model works. They are not real bank rates, fees, or offers. Each bank's numbers are similar to the others only for illustration.
A10: • Bank rates change often and some advertised rates depend on your balance, promotions, or conditions. Check the current terms directly with the bank before you rely on any result.
A11: • Fund fees (MER) shown for index funds and ETFs are illustrative, not the fee of any specific fund.
A13: How the results are calculated
A14: • Contributions are added once a year, and returns compound once a year. Monthly compounding would give slightly different results.
A15: • Returns are assumed to be fixed. Real investment returns vary from year to year and can be negative, so actual results may be lower or higher.
... A24: • Nothing in this file is financial, tax, legal, or investment advice. For decisions about your money, speak with a licensed professional who can consider your full situation.

Sheet Glossary
A1: Glossary: common terms, in plain English
A2: Short definitions for the terms used in this workbook and in Canadian banking. Checked against public sources in October 2026. Rules and limits change, so confirm with the CRA, the Government of Canada, or your bank before acting.
A4: Term | B4: Also called | C4: What it means | D4: Example | E4: Where you'll see it here
A5: GIC | B5: Guaranteed Investment Certificate; term deposit | C5: You lend money to a bank for a set period at a fixed rate. Deposits at CDIC member banks are insured up to $100,000 per category, with principal and interest combined. Cashing out early usually costs you interest. | D5: $10,000 at 3.5% for 1 year earns about $350 in interest. | E5: The '1-year GIC' rows on Bank Products.
A6: HISA | B6: High-interest savings account | C6: A savings account that pays more interest than a regular one. The rate can change at any time, but the money is easy to withdraw. | D6: $5,000 at 2% earns about $100 a year. | E6: The 'High-interest savings' rows on Bank Products.
A7: TFSA | B7: Tax-Free Savings Account | C7: A registered account where investments grow without tax. Withdrawals are tax-free, and the room comes back in January of the following year. If the investment lost value, the lost room is gone for good. The 2026 annual limit is $7,000. | D7: Growth inside the account is not taxed, even if it's large. | E7: Good for saving toward a house or other goals.
A8: FHSA | B8: First Home Savings Account | C8: A registered account for first-time home buyers who are Canadian residents aged 18 to 71. Contributions are tax-deductible, and qualifying withdrawals for a first home are tax-free. Limits: $8,000 a year and $40,000 for life, with unused annual room carried forward up to $8,000. The account must close by the earliest of: 15 years after opening, the year you turn 71, or the year after a qualifying withdrawal. | D8: Contributions reduce your taxable income in the year you make them. | E8: Relevant to the down payment goal on My Inputs. Check your eligibility.
A9: RRSP | B9: Registered Retirement Savings Plan | C9: A registered account for retirement. Contributions lower your taxable income now, but withdrawals are taxed later, with tax withheld at source. The 2026 limit is the lower of $33,810 or 18% of prior-year earned income, plus any carried-forward room. Room used by a withdrawal is not restored. | D9: Contributing $5,000 in a year where you pay tax at 30% can save about $1,500 in tax that year. | E9: Mostly for retirement, so it's less suited to a near-term house goal.
A10: Non-registered account | B10: Taxable investment account | C10: A regular investing account with no tax shelter. You pay tax on investment income and on profits when you sell. | D10: A $1,000 profit on a sale is taxed, depending on your tax bracket. | E10: The option when you've used up your TFSA or RRSP room.
A11: Interest rate | B11: Rate; APR (annual percentage rate) for loans | C11: The yearly cost of borrowing or the yearly return on savings, shown as a percentage of the amount. | D11: A 19.9% APR on a $4,000 balance adds about $800 in interest over a year if you pay nothing down. | E11: The APR on the debt inputs, and the rates on Bank Products.
A12: Compound interest | B12: Interest on interest | C12: You earn interest on your balance, and then the next period's interest is calculated on the bigger balance. | D12: $1,000 at 5%: $1,050 after year 1, then $1,102.50 after year 2. | E12: Why the Projection tab grows faster over time.
A13: Principal | B13: Original amount | C13: The amount you first invested or borrowed, before any interest. | D13: If you save $2,000 and it earns interest, $2,000 is the principal. | E13: Starting savings on My Inputs.
A14: Gross return | B14: Return before fees | C14: What an investment earns before any fees are taken out. | D14: A fund returning 6% before fees is a 6% gross return. | E14: The 'Gross annual return' column on Bank Products.
A15: Net return | B15: Return after fees | C15: What you actually keep after fees are taken out. This is the number that matters for your balance. | D15: 6% gross minus a 0.25% MER gives a 5.75% net return. | E15: Calculated automatically on Bank Products.
... A17: Account fee | B17: Annual fee | C17: A fixed fee in dollars that some accounts charge every year, separate from fund fees. | D17: A $50 yearly fee on a $2,000 balance is a 2.5% drag. | E17: The 'Yearly account fee' column on Bank Products.
A18: Mutual fund | C18: A pooled fund where a professional manager picks investments for many people. Usually has a higher MER than an ETF. | D18: Your $100 joins thousands of other people's money in one fund. | E18: One possible product type; check its MER first.
A19: ETF | B19: Exchange-traded fund | C19: A basket of investments that trades on the stock exchange like a single stock. Often has low fees. | D19: Buying one share of an ETF gives you a small piece of many companies. | E19: Often the 'Index fund / ETF' row on Bank Products.
A20: Index fund | B20: Passive fund | C20: A fund that copies a market index, such as the S&P/TSX Composite, instead of trying to beat it. Usually has low fees. | D20: An index fund holding the whole TSX tracks the index's returns. | E20: The 'Index fund / ETF' row on Bank Products.
A21: Stock | B21: Share; equity | C21: A piece of ownership in a company. Its price can rise or fall. | D21: Owning one share of a company makes you a part-owner. | E21: Usually held inside funds rather than bought directly.
A22: Bond | B22: Fixed-income investment | C22: A loan you make to a government or company, which pays you interest and returns your money on a set date. | D22: A $1,000 bond at 4% pays about $40 a year until it matures. | E22: Less common in this workbook, but often part of a fund.
A23: Capital gain | B23: Profit on a sale | C23: The profit when you sell an investment for more than you paid. | D23: Buying at $50 and selling at $70 is a $20 capital gain per share. | E23: Taxable in a non-registered account, not in a TFSA.
A24: Dividend | B24: Company payout | C24: A cash payment some companies make to shareholders from their profits. | D24: A $1 dividend per share on 100 shares pays you $100. | E24: Can be taxable in a non-registered account.
A25: Dollar-cost averaging | B25: Regular investing | C25: Investing the same amount on a set schedule, so you buy more when prices are low and less when they're high. | D25: Saving $500 a month into an index fund, no matter what the market is doing. | E25: The monthly savings amount on My Inputs.
A26: Inflation | B26: Rising prices | C26: The general increase in prices over time, which reduces what your money can buy. | D26: At 2% inflation, $100 buys about $98 of goods a year later. | E26: Not in the calculations, but it's why returns above inflation matter.
A27: Liquidity | B27: How easily you can access cash | C27: How quickly you can turn an investment into cash without losing much value. | D27: A HISA is very liquid; a GIC is less liquid because early withdrawal costs interest. | E27: Think about this before locking money into a GIC for a house.
A28: Down payment | B28: Upfront cash for a home | C28: The share of the home price you pay in cash. In Canada, paying less than 20% requires mortgage default insurance. Minimums are 5% on the first $500,000 and 10% on the portion above it. Homes priced at $1.5 million or more need 20% down. | D28: 10% of a $450,000 home is a $45,000 down payment. | E28: The down payment goal on My Inputs.
A29: Amortization | B29: Total repayment period | C29: The total time it takes to repay a mortgage in full. A mortgage term is the contract length, which is often shorter. | D29: A 25-year amortization with a 5-year term means you renegotiate every 5 years. | E29: Not in the model, but it affects how much interest you pay on a mortgage.
A30: Fixed vs variable rate | C30: A fixed rate stays the same for the term. A variable rate moves with the prime rate, so your payment can change. | D30: A 5% fixed rate stays at 5%; a variable rate at prime + 0.5% rises if prime rises. | E30: Relevant if you borrow for a home later.
A31: Prime rate | C31: The benchmark rate banks use to price variable-rate loans. Each bank sets its own, but it usually follows the Bank of Canada's overnight policy rate and sits a few points above it. | D31: If the prime rate rises by 0.25%, a variable mortgage at prime + 0.5% rises by the same amount. | E31: Relevant to variable-rate debt.
A32: Minimum payment | C32: The smallest amount you must pay on a debt each month. Paying only the minimum keeps you in debt much longer. | D32: On a $4,000 card, paying only the minimum can take years to clear. | E32: Relevant to any debt you're paying off.

Sheet My Inputs
A1: My Inputs
A2: Only edit the yellow cells.
A4: Monthly amount I can save | B4: 500 | C4: Money you can put aside each month.
A5: Down payment goal | B5: 45000 | C5: Example: 10% of a $450,000 home.
A6: Savings I already have | B6: 2000 | C6: Starting balance today.
A7: Years to project (1 to 30) | B7: 10 | C7: Change this to see results over a different timeframe.

Sheet Bank Products
A1: Bank Products (ILLUSTRATIVE numbers for this project only)
A2: Gross return = yearly rate before costs. Fee (MER) = yearly fund management fee. Account fee = fixed $ per year. Net return is calculated for you. All numbers on this tab are illustrative values made for this project. They are not real bank rates or fees.
A4: Bank | B4: Product | C4: Gross annual return | D4: Yearly fund fee (MER) | E4: Net annual return (calculated) | F4: Yearly account fee ($) | G4: Where to check / notes
A5: RBC | B5: High-interest savings | C5: 0.021 | D5: 0 | E5: =C5-D5 -> 0.021 | F5: 0 | G5: Illustrative value for this project, not a bank's rate
A6: RBC | B6: 1-year GIC | C6: 0.034 | D6: 0 | E6: =C6-D6 -> 0.034 | F6: 0 | G6: Illustrative value for this project, not a bank's rate
A7: RBC | B7: Index fund / ETF | C7: 0.06 | D7: 0.0025 | E7: =C7-D7 -> 0.0575 | F7: 0 | G7: Illustrative value for this project, not a bank's rate
A8: TD | B8: High-interest savings | C8: 0.02 | D8: 0 | E8: =C8-D8 -> 0.02 | F8: 0 | G8: Illustrative value for this project, not a bank's rate
A9: TD | B9: 1-year GIC | C9: 0.035 | D9: 0 | E9: =C9-D9 -> 0.035 | F9: 0 | G9: Illustrative value for this project, not a bank's rate
A10: TD | B10: Index fund / ETF | C10: 0.059 | D10: 0.003 | E10: =C10-D10 -> 0.056 | F10: 0 | G10: Illustrative value for this project, not a bank's rate
A11: BMO | B11: High-interest savings | C11: 0.0205 | D11: 0 | E11: =C11-D11 -> 0.0205 | F11: 0 | G11: Illustrative value for this project, not a bank's rate
A12: BMO | B12: 1-year GIC | C12: 0.0345 | D12: 0 | E12: =C12-D12 -> 0.0345 | F12: 0 | G12: Illustrative value for this project, not a bank's rate
A13: BMO | B13: Index fund / ETF | C13: 0.061 | D13: 0.002 | E13: =C13-D13 -> 0.059 | F13: 0 | G13: Illustrative value for this project, not a bank's rate
A14: Scotiabank | B14: High-interest savings | C14: 0.0195 | D14: 0 | E14: =C14-D14 -> 0.0195 | F14: 0 | G14: Illustrative value for this project, not a bank's rate
A15: Scotiabank | B15: 1-year GIC | C15: 0.036 | D15: 0 | E15: =C15-D15 -> 0.036 | F15: 0 | G15: Illustrative value for this project, not a bank's rate
A16: Scotiabank | B16: Index fund / ETF | C16: 0.058 | D16: 0.0035 | E16: =C16-D16 -> 0.0545 | F16: 0 | G16: Illustrative value for this project, not a bank's rate
... A19: CIBC | B19: Index fund / ETF | C19: 0.062 | D19: 0.0022 | E19: =C19-D19 -> 0.0598 | F19: 0 | G19: Illustrative value for this project, not a bank's rate

Sheet Projection
A1: Year | B1: ='Bank Products'!A5&" "&'Bank Products'!B5 -> RBC High-interest savings | C1: ='Bank Products'!A6&" "&'Bank Products'!B6 -> RBC 1-year GIC | D1: ='Bank Products'!A7&" "&'Bank Products'!B7 -> RBC Index fund / ETF | E1: ='Bank Products'!A8&" "&'Bank Products'!B8 -> TD High-interest savings | F1: ='Bank Products'!A9&" "&'Bank Products'!B9 -> TD 1-year GIC | G1: ='Bank Products'!A10&" "&'Bank Products'!B10 -> TD Index fund / ETF | H1: ='Bank Products'!A11&" "&'Bank Products'!B11 -> BMO High-interest savings | I1: ='Bank Products'!A12&" "&'Bank Products'!B12 -> BMO 1-year GIC | J1: ='Bank Products'!A13&" "&'Bank Products'!B13 -> BMO Index fund / ETF | K1: ='Bank Products'!A14&" "&'Bank Products'!B14 -> Scotiabank High-interest savings | L1: ='Bank Products'!A15&" "&'Bank Products'!B15 -> Scotiabank 1-year GIC | M1: ='Bank Products'!A16&" "&'Bank Products'!B16 -> Scotiabank Index fund / ETF | N1: ='Bank Products'!A17&" "&'Bank Products'!B17 -> CIBC High-interest savings | O1: ='Bank Products'!A18&" "&'Bank Products'!B18 -> CIBC 1-year GIC | P1: ='Bank Products'!A19&" "&'Bank Products'!B19 -> CIBC Index fund / ETF
A2: 0 | B2: ='My Inputs'!$B$6 -> 2000 | C2: ='My Inputs'!$B$6 -> 2000 | D2: ='My Inputs'!$B$6 -> 2000 | E2: ='My Inputs'!$B$6 -> 2000 | F2: ='My Inputs'!$B$6 -> 2000 | G2: ='My Inputs'!$B$6 -> 2000 | H2: ='My Inputs'!$B$6 -> 2000 | I2: ='My Inputs'!$B$6 -> 2000 | ... P2: ='My Inputs'!$B$6 -> 2000
A3: 1 | B3: =MAX(0,('My Inputs'!$B$4*12+B2)*(1+'Bank Products'!$E$5)-'Bank Products'!$F$5) -> 8168 | C3: =MAX(0,('My Inputs'!$B$4*12+C2)*(1+'Bank Products'!$E$6)-'Bank Products'!$F$6) -> 8272 | D3: =MAX(0,('My Inputs'!$B$4*12+D2)*(1+'Bank Products'!$E$7)-'Bank Products'!$F$7) -> 8460 | E3: =MAX(0,('My Inputs'!$B$4*12+E2)*(1+'Bank Products'!$E$8)-'Bank Products'!$F$8) -> 8160 | F3: =MAX(0,('My Inputs'!$B$4*12+F2)*(1+'Bank Products'!$E$9)-'Bank Products'!$F$9) -> 8280 | G3: =MAX(0,('My Inputs'!$B$4*12+G2)*(1+'Bank Products'!$E$10)-'Bank Products'!$F$10) -> 8448 | H3: =MAX(0,('My Inputs'!$B$4*12+H2)*(1+'Bank Products'!$E$11)-'Bank Products'!$F$11) -> 8164 | I3: =MAX(0,('My Inputs'!$B$4*12+I2)*(1+'Bank Products'!$E$12)-'Bank Products'!$F$12) -> 8276 | J3: =MAX(0,('My Inputs'!$B$4*12+J2)*(1+'Bank Products'!$E$13)-'Bank Products'!$F$13) -> 8472 | K3: =MAX(0,('My Inputs'!$B$4*12+K2)*(1+'Bank Products'!$E$14)-'Bank Products'!$F$14) -> 8156 | L3: =MAX(0,('My Inputs'!$B$4*12+L2)*(1+'Bank Products'!$E$15)-'Bank Products'!$F$15) -> 8288 | M3: =MAX(0,('My Inputs'!$B$4*12+M2)*(1+'Bank Products'!$E$16)-'Bank Products'!$F$16) -> 8436 | N3: =MAX(0,('My Inputs'!$B$4*12+N2)*(1+'Bank Products'!$E$17)-'Bank Products'!$F$17) -> 8172 | O3: =MAX(0,('My Inputs'!$B$4*12+O2)*(1+'Bank Products'!$E$18)-'Bank Products'!$F$18) -> 8264 | P3: =MAX(0,('My Inputs'!$B$4*12+P2)*(1+'Bank Products'!$E$19)-'Bank Products'!$F$19) -> 8478.4
A4: 2 | B4: =MAX(0,('My Inputs'!$B$4*12+B3)*(1+'Bank Products'!$E$5)-'Bank Products'!$F$5) -> 14465.528 | C4: =MAX(0,('My Inputs'!$B$4*12+C3)*(1+'Bank Products'!$E$6)-'Bank Products'!$F$6) -> 14757.248 | D4: =MAX(0,('My Inputs'!$B$4*12+D3)*(1+'Bank Products'!$E$7)-'Bank Products'!$F$7) -> 15291.45 | E4: =MAX(0,('My Inputs'!$B$4*12+E3)*(1+'Bank Products'!$E$8)-'Bank Products'!$F$8) -> 14443.2 | F4: =MAX(0,('My Inputs'!$B$4*12+F3)*(1+'Bank Products'!$E$9)-'Bank Products'!$F$9) -> 14779.8 | G4: =MAX(0,('My Inputs'!$B$4*12+G3)*(1+'Bank Products'!$E$10)-'Bank Products'!$F$10) -> 15257.088 | H4: =MAX(0,('My Inputs'!$B$4*12+H3)*(1+'Bank Products'!$E$11)-'Bank Products'!$F$11) -> 14454.362 | I4: =MAX(0,('My Inputs'!$B$4*12+I3)*(1+'Bank Products'!$E$12)-'Bank Products'!$F$12) -> 14768.522 | J4: =MAX(0,('My Inputs'!$B$4*12+J3)*(1+'Bank Products'!$E$13)-'Bank Products'!$F$13) -> 15325.848 | K4: =MAX(0,('My Inputs'!$B$4*12+K3)*(1+'Bank Products'!$E$14)-'Bank Products'!$F$14) -> 14432.042 | L4: =MAX(0,('My Inputs'!$B$4*12+L3)*(1+'Bank Products'!$E$15)-'Bank Products'!$F$15) -> 14802.368 | M4: =MAX(0,('My Inputs'!$B$4*12+M3)*(1+'Bank Products'!$E$16)-'Bank Products'!$F$16) -> 15222.762 | N4: =MAX(0,('My Inputs'!$B$4*12+N3)*(1+'Bank Products'!$E$17)-'Bank Products'!$F$17) -> 14476.698 | O4: =MAX(0,('My Inputs'!$B$4*12+O3)*(1+'Bank Products'!$E$18)-'Bank Products'!$F$18) -> 14734.712 | P4: =MAX(0,('My Inputs'!$B$4*12+P3)*(1+'Bank Products'!$E$19)-'Bank Products'!$F$19) -> 15344.208
A5: 3 | B5: =MAX(0,('My Inputs'!$B$4*12+B4)*(1+'Bank Products'!$E$5)-'Bank Products'!$F$5) -> 20895.304 | C5: =MAX(0,('My Inputs'!$B$4*12+C4)*(1+'Bank Products'!$E$6)-'Bank Products'!$F$6) -> 21462.994 | D5: =MAX(0,('My Inputs'!$B$4*12+D4)*(1+'Bank Products'!$E$7)-'Bank Products'!$F$7) -> 22515.708 | E5: =MAX(0,('My Inputs'!$B$4*12+E4)*(1+'Bank Products'!$E$8)-'Bank Products'!$F$8) -> 20852.064 | F5: =MAX(0,('My Inputs'!$B$4*12+F4)*(1+'Bank Products'!$E$9)-'Bank Products'!$F$9) -> 21507.093 | G5: =MAX(0,('My Inputs'!$B$4*12+G4)*(1+'Bank Products'!$E$10)-'Bank Products'!$F$10) -> 22447.485 | H5: =MAX(0,('My Inputs'!$B$4*12+H4)*(1+'Bank Products'!$E$11)-'Bank Products'!$F$11) -> 20873.676 | I5: =MAX(0,('My Inputs'!$B$4*12+I4)*(1+'Bank Products'!$E$12)-'Bank Products'!$F$12) -> 21485.036 | J5: =MAX(0,('My Inputs'!$B$4*12+J4)*(1+'Bank Products'!$E$13)-'Bank Products'!$F$13) -> 22584.073 | K5: =MAX(0,('My Inputs'!$B$4*12+K4)*(1+'Bank Products'!$E$14)-'Bank Products'!$F$14) -> 20830.467 | L5: =MAX(0,('My Inputs'!$B$4*12+L4)*(1+'Bank Products'!$E$15)-'Bank Products'!$F$15) -> 21551.253 | M5: =MAX(0,('My Inputs'!$B$4*12+M4)*(1+'Bank Products'!$E$16)-'Bank Products'!$F$16) -> 22379.403 | N5: =MAX(0,('My Inputs'!$B$4*12+N4)*(1+'Bank Products'!$E$17)-'Bank Products'!$F$17) -> 20916.947 | O5: =MAX(0,('My Inputs'!$B$4*12+O4)*(1+'Bank Products'!$E$18)-'Bank Products'!$F$18) -> 21418.957 | P5: =MAX(0,('My Inputs'!$B$4*12+P4)*(1+'Bank Products'!$E$19)-'Bank Products'!$F$19) -> 22620.592
A6: 4 | B6: =MAX(0,('My Inputs'!$B$4*12+B5)*(1+'Bank Products'!$E$5)-'Bank Products'!$F$5) -> 27460.105 | C6: =MAX(0,('My Inputs'!$B$4*12+C5)*(1+'Bank Products'!$E$6)-'Bank Products'!$F$6) -> 28396.736 | D6: =MAX(0,('My Inputs'!$B$4*12+D5)*(1+'Bank Products'!$E$7)-'Bank Products'!$F$7) -> 30155.362 | E6: =MAX(0,('My Inputs'!$B$4*12+E5)*(1+'Bank Products'!$E$8)-'Bank Products'!$F$8) -> 27389.105 | F6: =MAX(0,('My Inputs'!$B$4*12+F5)*(1+'Bank Products'!$E$9)-'Bank Products'!$F$9) -> 28469.841 | G6: =MAX(0,('My Inputs'!$B$4*12+G5)*(1+'Bank Products'!$E$10)-'Bank Products'!$F$10) -> 30040.544 | H6: =MAX(0,('My Inputs'!$B$4*12+H5)*(1+'Bank Products'!$E$11)-'Bank Products'!$F$11) -> 27424.587 | I6: =MAX(0,('My Inputs'!$B$4*12+I5)*(1+'Bank Products'!$E$12)-'Bank Products'!$F$12) -> 28433.27 | J6: =MAX(0,('My Inputs'!$B$4*12+J5)*(1+'Bank Products'!$E$13)-'Bank Products'!$F$13) -> 30270.533 | K6: =MAX(0,('My Inputs'!$B$4*12+K5)*(1+'Bank Products'!$E$14)-'Bank Products'!$F$14) -> 27353.661 | L6: =MAX(0,('My Inputs'!$B$4*12+L5)*(1+'Bank Products'!$E$15)-'Bank Products'!$F$15) -> 28543.098 | M6: =MAX(0,('My Inputs'!$B$4*12+M5)*(1+'Bank Products'!$E$16)-'Bank Products'!$F$16) -> 29926.08 | N6: =MAX(0,('My Inputs'!$B$4*12+N5)*(1+'Bank Products'!$E$17)-'Bank Products'!$F$17) -> 27495.661 | O6: =MAX(0,('My Inputs'!$B$4*12+O5)*(1+'Bank Products'!$E$18)-'Bank Products'!$F$18) -> 28323.783 | P6: =MAX(0,('My Inputs'!$B$4*12+P5)*(1+'Bank Products'!$E$19)-'Bank Products'!$F$19) -> 30332.103
A7: 5 | B7: =MAX(0,('My Inputs'!$B$4*12+B6)*(1+'Bank Products'!$E$5)-'Bank Products'!$F$5) -> 34162.768 | C7: =MAX(0,('My Inputs'!$B$4*12+C6)*(1+'Bank Products'!$E$6)-'Bank Products'!$F$6) -> 35566.225 | D7: =MAX(0,('My Inputs'!$B$4*12+D6)*(1+'Bank Products'!$E$7)-'Bank Products'!$F$7) -> 38234.295 | E7: =MAX(0,('My Inputs'!$B$4*12+E6)*(1+'Bank Products'!$E$8)-'Bank Products'!$F$8) -> 34056.887 | F7: =MAX(0,('My Inputs'!$B$4*12+F6)*(1+'Bank Products'!$E$9)-'Bank Products'!$F$9) -> 35676.286 | G7: =MAX(0,('My Inputs'!$B$4*12+G6)*(1+'Bank Products'!$E$10)-'Bank Products'!$F$10) -> 38058.815 | H7: =MAX(0,('My Inputs'!$B$4*12+H6)*(1+'Bank Products'!$E$11)-'Bank Products'!$F$11) -> 34109.791 | I7: =MAX(0,('My Inputs'!$B$4*12+I6)*(1+'Bank Products'!$E$12)-'Bank Products'!$F$12) -> 35621.218 | J7: =MAX(0,('My Inputs'!$B$4*12+J6)*(1+'Bank Products'!$E$13)-'Bank Products'!$F$13) -> 38410.495 | K7: =MAX(0,('My Inputs'!$B$4*12+K6)*(1+'Bank Products'!$E$14)-'Bank Products'!$F$14) -> 34004.057 | L7: =MAX(0,('My Inputs'!$B$4*12+L6)*(1+'Bank Products'!$E$15)-'Bank Products'!$F$15) -> 35786.65 | M7: =MAX(0,('My Inputs'!$B$4*12+M6)*(1+'Bank Products'!$E$16)-'Bank Products'!$F$16) -> 37884.051 | N7: =MAX(0,('My Inputs'!$B$4*12+N6)*(1+'Bank Products'!$E$17)-'Bank Products'!$F$17) -> 34215.818 | O7: =MAX(0,('My Inputs'!$B$4*12+O6)*(1+'Bank Products'!$E$18)-'Bank Products'!$F$18) -> 35456.468 | P7: =MAX(0,('My Inputs'!$B$4*12+P6)*(1+'Bank Products'!$E$19)-'Bank Products'!$F$19) -> 38504.763
A8: 6 | B8: =MAX(0,('My Inputs'!$B$4*12+B7)*(1+'Bank Products'!$E$5)-'Bank Products'!$F$5) -> 41006.186 | C8: =MAX(0,('My Inputs'!$B$4*12+C7)*(1+'Bank Products'!$E$6)-'Bank Products'!$F$6) -> 42979.477 | D8: =MAX(0,('My Inputs'!$B$4*12+D7)*(1+'Bank Products'!$E$7)-'Bank Products'!$F$7) -> 46777.767 | E8: =MAX(0,('My Inputs'!$B$4*12+E7)*(1+'Bank Products'!$E$8)-'Bank Products'!$F$8) -> 40858.025 | F8: =MAX(0,('My Inputs'!$B$4*12+F7)*(1+'Bank Products'!$E$9)-'Bank Products'!$F$9) -> 43134.956 | G8: =MAX(0,('My Inputs'!$B$4*12+G7)*(1+'Bank Products'!$E$10)-'Bank Products'!$F$10) -> 46526.108 | H8: =MAX(0,('My Inputs'!$B$4*12+H7)*(1+'Bank Products'!$E$11)-'Bank Products'!$F$11) -> 40932.042 | I8: =MAX(0,('My Inputs'!$B$4*12+I7)*(1+'Bank Products'!$E$12)-'Bank Products'!$F$12) -> 43057.15 | J8: =MAX(0,('My Inputs'!$B$4*12+J7)*(1+'Bank Products'!$E$13)-'Bank Products'!$F$13) -> 47030.714 | K8: =MAX(0,('My Inputs'!$B$4*12+K7)*(1+'Bank Products'!$E$14)-'Bank Products'!$F$14) -> 40784.136 | L8: =MAX(0,('My Inputs'!$B$4*12+L7)*(1+'Bank Products'!$E$15)-'Bank Products'!$F$15) -> 43290.969 | M8: =MAX(0,('My Inputs'!$B$4*12+M7)*(1+'Bank Products'!$E$16)-'Bank Products'!$F$16) -> 46275.732 | N8: =MAX(0,('My Inputs'!$B$4*12+N7)*(1+'Bank Products'!$E$17)-'Bank Products'!$F$17) -> 41080.458 | O8: =MAX(0,('My Inputs'!$B$4*12+O7)*(1+'Bank Products'!$E$18)-'Bank Products'!$F$18) -> 42824.531 | P8: =MAX(0,('My Inputs'!$B$4*12+P7)*(1+'Bank Products'!$E$19)-'Bank Products'!$F$19) -> 47166.148
A9: 7 | B9: =MAX(0,('My Inputs'!$B$4*12+B8)*(1+'Bank Products'!$E$5)-'Bank Products'!$F$5) -> 47993.316 | C9: =MAX(0,('My Inputs'!$B$4*12+C8)*(1+'Bank Products'!$E$6)-'Bank Products'!$F$6) -> 50644.779 | D9: =MAX(0,('My Inputs'!$B$4*12+D8)*(1+'Bank Products'!$E$7)-'Bank Products'!$F$7) -> 55812.488 | E9: =MAX(0,('My Inputs'!$B$4*12+E8)*(1+'Bank Products'!$E$8)-'Bank Products'!$F$8) -> 47795.186 | F9: =MAX(0,('My Inputs'!$B$4*12+F8)*(1+'Bank Products'!$E$9)-'Bank Products'!$F$9) -> 50854.679 | G9: =MAX(0,('My Inputs'!$B$4*12+G8)*(1+'Bank Products'!$E$10)-'Bank Products'!$F$10) -> 55467.57 | H9: =MAX(0,('My Inputs'!$B$4*12+H8)*(1+'Bank Products'!$E$11)-'Bank Products'!$F$11) -> 47894.148 | I9: =MAX(0,('My Inputs'!$B$4*12+I8)*(1+'Bank Products'!$E$12)-'Bank Products'!$F$12) -> 50749.621 | J9: =MAX(0,('My Inputs'!$B$4*12+J8)*(1+'Bank Products'!$E$13)-'Bank Products'!$F$13) -> 56159.526 | K9: =MAX(0,('My Inputs'!$B$4*12+K8)*(1+'Bank Products'!$E$14)-'Bank Products'!$F$14) -> 47696.427 | L9: =MAX(0,('My Inputs'!$B$4*12+L8)*(1+'Bank Products'!$E$15)-'Bank Products'!$F$15) -> 51065.444 | M9: =MAX(0,('My Inputs'!$B$4*12+M8)*(1+'Bank Products'!$E$16)-'Bank Products'!$F$16) -> 55124.76 | N9: =MAX(0,('My Inputs'!$B$4*12+N8)*(1+'Bank Products'!$E$17)-'Bank Products'!$F$17) -> 48092.688 | O9: =MAX(0,('My Inputs'!$B$4*12+O8)*(1+'Bank Products'!$E$18)-'Bank Products'!$F$18) -> 50435.741 | P9: =MAX(0,('My Inputs'!$B$4*12+P8)*(1+'Bank Products'!$E$19)-'Bank Products'!$F$19) -> 56345.484
A10: 8 | B10: =MAX(0,('My Inputs'!$B$4*12+B9)*(1+'Bank Products'!$E$5)-'Bank Products'!$F$5) -> 55127.175 | C10: =MAX(0,('My Inputs'!$B$4*12+C9)*(1+'Bank Products'!$E$6)-'Bank Products'!$F$6) -> 58570.702 | D10: =MAX(0,('My Inputs'!$B$4*12+D9)*(1+'Bank Products'!$E$7)-'Bank Products'!$F$7) -> 65366.707 | E10: =MAX(0,('My Inputs'!$B$4*12+E9)*(1+'Bank Products'!$E$8)-'Bank Products'!$F$8) -> 54871.089 | F10: =MAX(0,('My Inputs'!$B$4*12+F9)*(1+'Bank Products'!$E$9)-'Bank Products'!$F$9) -> 58844.593 | G10: =MAX(0,('My Inputs'!$B$4*12+G9)*(1+'Bank Products'!$E$10)-'Bank Products'!$F$10) -> 64909.754 | H10: =MAX(0,('My Inputs'!$B$4*12+H9)*(1+'Bank Products'!$E$11)-'Bank Products'!$F$11) -> 54998.978 | I10: =MAX(0,('My Inputs'!$B$4*12+I9)*(1+'Bank Products'!$E$12)-'Bank Products'!$F$12) -> 58707.483 | J10: =MAX(0,('My Inputs'!$B$4*12+J9)*(1+'Bank Products'!$E$13)-'Bank Products'!$F$13) -> 65826.938 | K10: =MAX(0,('My Inputs'!$B$4*12+K9)*(1+'Bank Products'!$E$14)-'Bank Products'!$F$14) -> 54743.507 | L10: =MAX(0,('My Inputs'!$B$4*12+L9)*(1+'Bank Products'!$E$15)-'Bank Products'!$F$15) -> 59119.8 | M10: =MAX(0,('My Inputs'!$B$4*12+M9)*(1+'Bank Products'!$E$16)-'Bank Products'!$F$16) -> 64456.059 | N10: =MAX(0,('My Inputs'!$B$4*12+N9)*(1+'Bank Products'!$E$17)-'Bank Products'!$F$17) -> 55255.681 | O10: =MAX(0,('My Inputs'!$B$4*12+O9)*(1+'Bank Products'!$E$18)-'Bank Products'!$F$18) -> 58298.12 | P10: =MAX(0,('My Inputs'!$B$4*12+P9)*(1+'Bank Products'!$E$19)-'Bank Products'!$F$19) -> 66073.744
A11: 9 | B11: =MAX(0,('My Inputs'!$B$4*12+B10)*(1+'Bank Products'!$E$5)-'Bank Products'!$F$5) -> 62410.846 | C11: =MAX(0,('My Inputs'!$B$4*12+C10)*(1+'Bank Products'!$E$6)-'Bank Products'!$F$6) -> 66766.105 | D11: =MAX(0,('My Inputs'!$B$4*12+D10)*(1+'Bank Products'!$E$7)-'Bank Products'!$F$7) -> 75470.292 | E11: =MAX(0,('My Inputs'!$B$4*12+E10)*(1+'Bank Products'!$E$8)-'Bank Products'!$F$8) -> 62088.511 | F11: =MAX(0,('My Inputs'!$B$4*12+F10)*(1+'Bank Products'!$E$9)-'Bank Products'!$F$9) -> 67114.154 | G11: =MAX(0,('My Inputs'!$B$4*12+G10)*(1+'Bank Products'!$E$10)-'Bank Products'!$F$10) -> 74880.7 | H11: =MAX(0,('My Inputs'!$B$4*12+H10)*(1+'Bank Products'!$E$11)-'Bank Products'!$F$11) -> 62249.457 | I11: =MAX(0,('My Inputs'!$B$4*12+I10)*(1+'Bank Products'!$E$12)-'Bank Products'!$F$12) -> 66939.891 | J11: =MAX(0,('My Inputs'!$B$4*12+J10)*(1+'Bank Products'!$E$13)-'Bank Products'!$F$13) -> 76064.728 | K11: =MAX(0,('My Inputs'!$B$4*12+K10)*(1+'Bank Products'!$E$14)-'Bank Products'!$F$14) -> 61928.006 | L11: =MAX(0,('My Inputs'!$B$4*12+L10)*(1+'Bank Products'!$E$15)-'Bank Products'!$F$15) -> 67464.113 | M11: =MAX(0,('My Inputs'!$B$4*12+M10)*(1+'Bank Products'!$E$16)-'Bank Products'!$F$16) -> 74295.914 | N11: =MAX(0,('My Inputs'!$B$4*12+N10)*(1+'Bank Products'!$E$17)-'Bank Products'!$F$17) -> 62572.678 | O11: =MAX(0,('My Inputs'!$B$4*12+O10)*(1+'Bank Products'!$E$18)-'Bank Products'!$F$18) -> 66419.958 | P11: =MAX(0,('My Inputs'!$B$4*12+P10)*(1+'Bank Products'!$E$19)-'Bank Products'!$F$19) -> 76383.753
A12: 10 | B12: =MAX(0,('My Inputs'!$B$4*12+B11)*(1+'Bank Products'!$E$5)-'Bank Products'!$F$5) -> 69847.474 | C12: =MAX(0,('My Inputs'!$B$4*12+C11)*(1+'Bank Products'!$E$6)-'Bank Products'!$F$6) -> 75240.153 | D12: =MAX(0,('My Inputs'!$B$4*12+D11)*(1+'Bank Products'!$E$7)-'Bank Products'!$F$7) -> 86154.834 | E12: =MAX(0,('My Inputs'!$B$4*12+E11)*(1+'Bank Products'!$E$8)-'Bank Products'!$F$8) -> 69450.281 | F12: =MAX(0,('My Inputs'!$B$4*12+F11)*(1+'Bank Products'!$E$9)-'Bank Products'!$F$9) -> 75673.149 | G12: =MAX(0,('My Inputs'!$B$4*12+G11)*(1+'Bank Products'!$E$10)-'Bank Products'!$F$10) -> 85410.02 | H12: =MAX(0,('My Inputs'!$B$4*12+H11)*(1+'Bank Products'!$E$11)-'Bank Products'!$F$11) -> 69648.571 | I12: =MAX(0,('My Inputs'!$B$4*12+I11)*(1+'Bank Products'!$E$12)-'Bank Products'!$F$12) -> 75456.318 | J12: =MAX(0,('My Inputs'!$B$4*12+J11)*(1+'Bank Products'!$E$13)-'Bank Products'!$F$13) -> 86906.546 | K12: =MAX(0,('My Inputs'!$B$4*12+K11)*(1+'Bank Products'!$E$14)-'Bank Products'!$F$14) -> 69252.602 | L12: =MAX(0,('My Inputs'!$B$4*12+L11)*(1+'Bank Products'!$E$15)-'Bank Products'!$F$15) -> 76108.821 | M12: =MAX(0,('My Inputs'!$B$4*12+M11)*(1+'Bank Products'!$E$16)-'Bank Products'!$F$16) -> 84672.041 | N12: =MAX(0,('My Inputs'!$B$4*12+N11)*(1+'Bank Products'!$E$17)-'Bank Products'!$F$17) -> 70046.991 | O12: =MAX(0,('My Inputs'!$B$4*12+O11)*(1+'Bank Products'!$E$18)-'Bank Products'!$F$18) -> 74809.817 | P12: =MAX(0,('My Inputs'!$B$4*12+P11)*(1+'Bank Products'!$E$19)-'Bank Products'!$F$19) -> 87310.302
A13: 11 | B13: =MAX(0,('My Inputs'!$B$4*12+B12)*(1+'Bank Products'!$E$5)-'Bank Products'!$F$5) -> 77440.271 | C13: =MAX(0,('My Inputs'!$B$4*12+C12)*(1+'Bank Products'!$E$6)-'Bank Products'!$F$6) -> 84002.318 | D13: =MAX(0,('My Inputs'!$B$4*12+D12)*(1+'Bank Products'!$E$7)-'Bank Products'!$F$7) -> 97453.737 | E13: =MAX(0,('My Inputs'!$B$4*12+E12)*(1+'Bank Products'!$E$8)-'Bank Products'!$F$8) -> 76959.287 | F13: =MAX(0,('My Inputs'!$B$4*12+F12)*(1+'Bank Products'!$E$9)-'Bank Products'!$F$9) -> 84531.709 | G13: =MAX(0,('My Inputs'!$B$4*12+G12)*(1+'Bank Products'!$E$10)-'Bank Products'!$F$10) -> 96528.981 | H13: =MAX(0,('My Inputs'!$B$4*12+H12)*(1+'Bank Products'!$E$11)-'Bank Products'!$F$11) -> 77199.367 | I13: =MAX(0,('My Inputs'!$B$4*12+I12)*(1+'Bank Products'!$E$12)-'Bank Products'!$F$12) -> 84266.561 | J13: =MAX(0,('My Inputs'!$B$4*12+J12)*(1+'Bank Products'!$E$13)-'Bank Products'!$F$13) -> 98388.033 | K13: =MAX(0,('My Inputs'!$B$4*12+K12)*(1+'Bank Products'!$E$14)-'Bank Products'!$F$14) -> 76720.028 | L13: =MAX(0,('My Inputs'!$B$4*12+L12)*(1+'Bank Products'!$E$15)-'Bank Products'!$F$15) -> 85064.739 | M13: =MAX(0,('My Inputs'!$B$4*12+M12)*(1+'Bank Products'!$E$16)-'Bank Products'!$F$16) -> 95613.668 | N13: =MAX(0,('My Inputs'!$B$4*12+N12)*(1+'Bank Products'!$E$17)-'Bank Products'!$F$17) -> 77682.001 | O13: =MAX(0,('My Inputs'!$B$4*12+O12)*(1+'Bank Products'!$E$18)-'Bank Products'!$F$18) -> 83476.541 | P13: =MAX(0,('My Inputs'!$B$4*12+P12)*(1+'Bank Products'!$E$19)-'Bank Products'!$F$19) -> 98890.258
A14: 12 | B14: =MAX(0,('My Inputs'!$B$4*12+B13)*(1+'Bank Products'!$E$5)-'Bank Products'!$F$5) -> 85192.516 | C14: =MAX(0,('My Inputs'!$B$4*12+C13)*(1+'Bank Products'!$E$6)-'Bank Products'!$F$6) -> 93062.397 | D14: =MAX(0,('My Inputs'!$B$4*12+D13)*(1+'Bank Products'!$E$7)-'Bank Products'!$F$7) -> 109402.33 | E14: =MAX(0,('My Inputs'!$B$4*12+E13)*(1+'Bank Products'!$E$8)-'Bank Products'!$F$8) -> 84618.473 | F14: =MAX(0,('My Inputs'!$B$4*12+F13)*(1+'Bank Products'!$E$9)-'Bank Products'!$F$9) -> 93700.319 | G14: =MAX(0,('My Inputs'!$B$4*12+G13)*(1+'Bank Products'!$E$10)-'Bank Products'!$F$10) -> 108270.6 | H14: =MAX(0,('My Inputs'!$B$4*12+H13)*(1+'Bank Products'!$E$11)-'Bank Products'!$F$11) -> 84904.954 | I14: =MAX(0,('My Inputs'!$B$4*12+I13)*(1+'Bank Products'!$E$12)-'Bank Products'!$F$12) -> 93380.757 | J14: =MAX(0,('My Inputs'!$B$4*12+J13)*(1+'Bank Products'!$E$13)-'Bank Products'!$F$13) -> 110546.93 | K14: =MAX(0,('My Inputs'!$B$4*12+K13)*(1+'Bank Products'!$E$14)-'Bank Products'!$F$14) -> 84333.068 | L14: =MAX(0,('My Inputs'!$B$4*12+L13)*(1+'Bank Products'!$E$15)-'Bank Products'!$F$15) -> 94343.069 | M14: =MAX(0,('My Inputs'!$B$4*12+M13)*(1+'Bank Products'!$E$16)-'Bank Products'!$F$16) -> 107151.61 | N14: =MAX(0,('My Inputs'!$B$4*12+N13)*(1+'Bank Products'!$E$17)-'Bank Products'!$F$17) -> 85481.164 | O14: =MAX(0,('My Inputs'!$B$4*12+O13)*(1+'Bank Products'!$E$18)-'Bank Products'!$F$18) -> 92429.267 | P14: =MAX(0,('My Inputs'!$B$4*12+P13)*(1+'Bank Products'!$E$19)-'Bank Products'!$F$19) -> 111162.7
... A32: 30 | B32: =MAX(0,('My Inputs'!$B$4*12+B31)*(1+'Bank Products'!$E$5)-'Bank Products'!$F$5) -> 256180.71 | C32: =MAX(0,('My Inputs'!$B$4*12+C31)*(1+'Bank Products'!$E$6)-'Bank Products'!$F$6) -> 320500.82 | D32: =MAX(0,('My Inputs'!$B$4*12+D31)*(1+'Bank Products'!$E$7)-'Bank Products'!$F$7) -> 490792.63 | E32: =MAX(0,('My Inputs'!$B$4*12+E31)*(1+'Bank Products'!$E$8)-'Bank Products'!$F$8) -> 251899.37 | F32: =MAX(0,('My Inputs'!$B$4*12+F31)*(1+'Bank Products'!$E$9)-'Bank Products'!$F$9) -> 326190.41 | G32: =MAX(0,('My Inputs'!$B$4*12+G31)*(1+'Bank Products'!$E$10)-'Bank Products'!$F$10) -> 477268.29 | H32: =MAX(0,('My Inputs'!$B$4*12+H31)*(1+'Bank Products'!$E$11)-'Bank Products'!$F$11) -> 254029.26 | I32: =MAX(0,('My Inputs'!$B$4*12+I31)*(1+'Bank Products'!$E$12)-'Bank Products'!$F$12) -> 323331.05 | J32: =MAX(0,('My Inputs'!$B$4*12+J31)*(1+'Bank Products'!$E$13)-'Bank Products'!$F$13) -> 504747.56 | K32: =MAX(0,('My Inputs'!$B$4*12+K31)*(1+'Bank Products'!$E$14)-'Bank Products'!$F$14) -> 249790.8 | L32: =MAX(0,('My Inputs'!$B$4*12+L31)*(1+'Bank Products'!$E$15)-'Bank Products'!$F$15) -> 331997.76 | M32: =MAX(0,('My Inputs'!$B$4*12+M31)*(1+'Bank Products'!$E$16)-'Bank Products'!$F$16) -> 464160.8 | N32: =MAX(0,('My Inputs'!$B$4*12+N31)*(1+'Bank Products'!$E$17)-'Bank Products'!$F$17) -> 258353.95 | O32: =MAX(0,('My Inputs'!$B$4*12+O31)*(1+'Bank Products'!$E$18)-'Bank Products'!$F$18) -> 314926.46 | P32: =MAX(0,('My Inputs'!$B$4*12+P31)*(1+'Bank Products'!$E$19)-'Bank Products'!$F$19) -> 512371.13

Sheet Dashboard
A1: Dashboard: Where should my savings go?
A2: Everything here updates from My Inputs and Bank Products. Rates and fees are illustrative values for this project, not real bank offers.
A4: Best option for my timeframe: | B4: =INDEX($A$9:$A$23,MATCH(MAX($C$9:$C$23),$C$9:$C$23,0))&" "&INDEX($B$9:$B$23,MATCH(MAX($C$9:$C$23),$C$9:$C$23,0)) -> CIBC Index fund / ETF
A5: Balance it reaches: | B5: =MAX($C$9:$C$23) -> 87310.302
A6: Years to reach my down payment goal: | B6: =INDEX($F$9:$F$23,MATCH(MAX($C$9:$C$23),$C$9:$C$23,0)) -> 6
A7: All schemes compared
A8: Bank | B8: Product | C8: Balance after my timeframe | D8: Total I put in | E8: Growth from returns (after fees) | F8: Years to reach down payment | G8: Rank (1 = best) | H8: Highest | I8: Other schemes | J8: Bank and scheme
A9: ='Bank Products'!A5 -> RBC | B9: ='Bank Products'!B5 -> High-interest savings | C9: =INDEX(Projection!B$2:B$32,'My Inputs'!$B$7+1) -> 69847.474 | D9: ='My Inputs'!$B$6+12*'My Inputs'!$B$4*'My Inputs'!$B$7 -> 62000 | E9: =C9-D9 -> 7847.4738 | F9: =IF(COUNTIF(Projection!B$2:B$32,"<"&'My Inputs'!$B$5)>30,"Not in 30 yrs",COUNTIF(Projection!B$2:B$32,"<"&'My Inputs'!$B$5)) -> 7 | G9: =RANK(C9,$C$9:$C$23) -> 12 | H9: =IF(C9=MAX($C$9:$C$23),C9,0) -> 0 | I9: =IF(C9=MAX($C$9:$C$23),0,C9) -> 69847.474 | J9: =A9&" "&B9 -> RBC High-interest savings
A10: ='Bank Products'!A6 -> RBC | B10: ='Bank Products'!B6 -> 1-year GIC | C10: =INDEX(Projection!C$2:C$32,'My Inputs'!$B$7+1) -> 75240.153 | D10: ='My Inputs'!$B$6+12*'My Inputs'!$B$4*'My Inputs'!$B$7 -> 62000 | E10: =C10-D10 -> 13240.153 | F10: =IF(COUNTIF(Projection!C$2:C$32,"<"&'My Inputs'!$B$5)>30,"Not in 30 yrs",COUNTIF(Projection!C$2:C$32,"<"&'My Inputs'!$B$5)) -> 7 | G10: =RANK(C10,$C$9:$C$23) -> 9 | H10: =IF(C10=MAX($C$9:$C$23),C10,0) -> 0 | I10: =IF(C10=MAX($C$9:$C$23),0,C10) -> 75240.153 | J10: =A10&" "&B10 -> RBC 1-year GIC
A11: ='Bank Products'!A7 -> RBC | B11: ='Bank Products'!B7 -> Index fund / ETF | C11: =INDEX(Projection!D$2:D$32,'My Inputs'!$B$7+1) -> 86154.834 | D11: ='My Inputs'!$B$6+12*'My Inputs'!$B$4*'My Inputs'!$B$7 -> 62000 | E11: =C11-D11 -> 24154.834 | F11: =IF(COUNTIF(Projection!D$2:D$32,"<"&'My Inputs'!$B$5)>30,"Not in 30 yrs",COUNTIF(Projection!D$2:D$32,"<"&'My Inputs'!$B$5)) -> 6 | G11: =RANK(C11,$C$9:$C$23) -> 3 | H11: =IF(C11=MAX($C$9:$C$23),C11,0) -> 0 | I11: =IF(C11=MAX($C$9:$C$23),0,C11) -> 86154.834 | J11: =A11&" "&B11 -> RBC Index fund / ETF
A12: ='Bank Products'!A8 -> TD | B12: ='Bank Products'!B8 -> High-interest savings | C12: =INDEX(Projection!E$2:E$32,'My Inputs'!$B$7+1) -> 69450.281 | D12: ='My Inputs'!$B$6+12*'My Inputs'!$B$4*'My Inputs'!$B$7 -> 62000 | E12: =C12-D12 -> 7450.2814 | F12: =IF(COUNTIF(Projection!E$2:E$32,"<"&'My Inputs'!$B$5)>30,"Not in 30 yrs",COUNTIF(Projection!E$2:E$32,"<"&'My Inputs'!$B$5)) -> 7 | G12: =RANK(C12,$C$9:$C$23) -> 14 | H12: =IF(C12=MAX($C$9:$C$23),C12,0) -> 0 | I12: =IF(C12=MAX($C$9:$C$23),0,C12) -> 69450.281 | J12: =A12&" "&B12 -> TD High-interest savings
A13: ='Bank Products'!A9 -> TD | B13: ='Bank Products'!B9 -> 1-year GIC | C13: =INDEX(Projection!F$2:F$32,'My Inputs'!$B$7+1) -> 75673.149 | D13: ='My Inputs'!$B$6+12*'My Inputs'!$B$4*'My Inputs'!$B$7 -> 62000 | E13: =C13-D13 -> 13673.149 | F13: =IF(COUNTIF(Projection!F$2:F$32,"<"&'My Inputs'!$B$5)>30,"Not in 30 yrs",COUNTIF(Projection!F$2:F$32,"<"&'My Inputs'!$B$5)) -> 7 | G13: =RANK(C13,$C$9:$C$23) -> 7 | H13: =IF(C13=MAX($C$9:$C$23),C13,0) -> 0 | I13: =IF(C13=MAX($C$9:$C$23),0,C13) -> 75673.149 | J13: =A13&" "&B13 -> TD 1-year GIC
A14: ='Bank Products'!A10 -> TD | B14: ='Bank Products'!B10 -> Index fund / ETF | C14: =INDEX(Projection!G$2:G$32,'My Inputs'!$B$7+1) -> 85410.02 | D14: ='My Inputs'!$B$6+12*'My Inputs'!$B$4*'My Inputs'!$B$7 -> 62000 | E14: =C14-D14 -> 23410.02 | F14: =IF(COUNTIF(Projection!G$2:G$32,"<"&'My Inputs'!$B$5)>30,"Not in 30 yrs",COUNTIF(Projection!G$2:G$32,"<"&'My Inputs'!$B$5)) -> 6 | G14: =RANK(C14,$C$9:$C$23) -> 4 | H14: =IF(C14=MAX($C$9:$C$23),C14,0) -> 0 | I14: =IF(C14=MAX($C$9:$C$23),0,C14) -> 85410.02 | J14: =A14&" "&B14 -> TD Index fund / ETF
A15: ='Bank Products'!A11 -> BMO | B15: ='Bank Products'!B11 -> High-interest savings | C15: =INDEX(Projection!H$2:H$32,'My Inputs'!$B$7+1) -> 69648.571 | D15: ='My Inputs'!$B$6+12*'My Inputs'!$B$4*'My Inputs'!$B$7 -> 62000 | E15: =C15-D15 -> 7648.5714 | F15: =IF(COUNTIF(Projection!H$2:H$32,"<"&'My Inputs'!$B$5)>30,"Not in 30 yrs",COUNTIF(Projection!H$2:H$32,"<"&'My Inputs'!$B$5)) -> 7 | G15: =RANK(C15,$C$9:$C$23) -> 13 | H15: =IF(C15=MAX($C$9:$C$23),C15,0) -> 0 | I15: =IF(C15=MAX($C$9:$C$23),0,C15) -> 69648.571 | J15: =A15&" "&B15 -> BMO High-interest savings
A16: ='Bank Products'!A12 -> BMO | B16: ='Bank Products'!B12 -> 1-year GIC | C16: =INDEX(Projection!I$2:I$32,'My Inputs'!$B$7+1) -> 75456.318 | D16: ='My Inputs'!$B$6+12*'My Inputs'!$B$4*'My Inputs'!$B$7 -> 62000 | E16: =C16-D16 -> 13456.318 | F16: =IF(COUNTIF(Projection!I$2:I$32,"<"&'My Inputs'!$B$5)>30,"Not in 30 yrs",COUNTIF(Projection!I$2:I$32,"<"&'My Inputs'!$B$5)) -> 7 | G16: =RANK(C16,$C$9:$C$23) -> 8 | H16: =IF(C16=MAX($C$9:$C$23),C16,0) -> 0 | I16: =IF(C16=MAX($C$9:$C$23),0,C16) -> 75456.318 | J16: =A16&" "&B16 -> BMO 1-year GIC
A17: ='Bank Products'!A13 -> BMO | B17: ='Bank Products'!B13 -> Index fund / ETF | C17: =INDEX(Projection!J$2:J$32,'My Inputs'!$B$7+1) -> 86906.546 | D17: ='My Inputs'!$B$6+12*'My Inputs'!$B$4*'My Inputs'!$B$7 -> 62000 | E17: =C17-D17 -> 24906.546 | F17: =IF(COUNTIF(Projection!J$2:J$32,"<"&'My Inputs'!$B$5)>30,"Not in 30 yrs",COUNTIF(Projection!J$2:J$32,"<"&'My Inputs'!$B$5)) -> 6 | G17: =RANK(C17,$C$9:$C$23) -> 2 | H17: =IF(C17=MAX($C$9:$C$23),C17,0) -> 0 | I17: =IF(C17=MAX($C$9:$C$23),0,C17) -> 86906.546 | J17: =A17&" "&B17 -> BMO Index fund / ETF
A18: ='Bank Products'!A14 -> Scotiabank | B18: ='Bank Products'!B14 -> High-interest savings | C18: =INDEX(Projection!K$2:K$32,'My Inputs'!$B$7+1) -> 69252.602 | D18: ='My Inputs'!$B$6+12*'My Inputs'!$B$4*'My Inputs'!$B$7 -> 62000 | E18: =C18-D18 -> 7252.6019 | F18: =IF(COUNTIF(Projection!K$2:K$32,"<"&'My Inputs'!$B$5)>30,"Not in 30 yrs",COUNTIF(Projection!K$2:K$32,"<"&'My Inputs'!$B$5)) -> 7 | G18: =RANK(C18,$C$9:$C$23) -> 15 | H18: =IF(C18=MAX($C$9:$C$23),C18,0) -> 0 | I18: =IF(C18=MAX($C$9:$C$23),0,C18) -> 69252.602 | J18: =A18&" "&B18 -> Scotiabank High-interest savings
A19: ='Bank Products'!A15 -> Scotiabank | B19: ='Bank Products'!B15 -> 1-year GIC | C19: =INDEX(Projection!L$2:L$32,'My Inputs'!$B$7+1) -> 76108.821 | D19: ='My Inputs'!$B$6+12*'My Inputs'!$B$4*'My Inputs'!$B$7 -> 62000 | E19: =C19-D19 -> 14108.821 | F19: =IF(COUNTIF(Projection!L$2:L$32,"<"&'My Inputs'!$B$5)>30,"Not in 30 yrs",COUNTIF(Projection!L$2:L$32,"<"&'My Inputs'!$B$5)) -> 7 | G19: =RANK(C19,$C$9:$C$23) -> 6 | H19: =IF(C19=MAX($C$9:$C$23),C19,0) -> 0 | I19: =IF(C19=MAX($C$9:$C$23),0,C19) -> 76108.821 | J19: =A19&" "&B19 -> Scotiabank 1-year GIC
A20: ='Bank Products'!A16 -> Scotiabank | B20: ='Bank Products'!B16 -> Index fund / ETF | C20: =INDEX(Projection!M$2:M$32,'My Inputs'!$B$7+1) -> 84672.041 | D20: ='My Inputs'!$B$6+12*'My Inputs'!$B$4*'My Inputs'!$B$7 -> 62000 | E20: =C20-D20 -> 22672.041 | F20: =IF(COUNTIF(Projection!M$2:M$32,"<"&'My Inputs'!$B$5)>30,"Not in 30 yrs",COUNTIF(Projection!M$2:M$32,"<"&'My Inputs'!$B$5)) -> 6 | G20: =RANK(C20,$C$9:$C$23) -> 5 | H20: =IF(C20=MAX($C$9:$C$23),C20,0) -> 0 | I20: =IF(C20=MAX($C$9:$C$23),0,C20) -> 84672.041 | J20: =A20&" "&B20 -> Scotiabank Index fund / ETF
A21: ='Bank Products'!A17 -> CIBC | B21: ='Bank Products'!B17 -> High-interest savings | C21: =INDEX(Projection!N$2:N$32,'My Inputs'!$B$7+1) -> 70046.991 | D21: ='My Inputs'!$B$6+12*'My Inputs'!$B$4*'My Inputs'!$B$7 -> 62000 | E21: =C21-D21 -> 8046.9905 | F21: =IF(COUNTIF(Projection!N$2:N$32,"<"&'My Inputs'!$B$5)>30,"Not in 30 yrs",COUNTIF(Projection!N$2:N$32,"<"&'My Inputs'!$B$5)) -> 7 | G21: =RANK(C21,$C$9:$C$23) -> 11 | H21: =IF(C21=MAX($C$9:$C$23),C21,0) -> 0 | I21: =IF(C21=MAX($C$9:$C$23),0,C21) -> 70046.991 | J21: =A21&" "&B21 -> CIBC High-interest savings
A22: ='Bank Products'!A18 -> CIBC | B22: ='Bank Products'!B18 -> 1-year GIC | C22: =INDEX(Projection!O$2:O$32,'My Inputs'!$B$7+1) -> 74809.817 | D22: ='My Inputs'!$B$6+12*'My Inputs'!$B$4*'My Inputs'!$B$7 -> 62000 | E22: =C22-D22 -> 12809.817 | F22: =IF(COUNTIF(Projection!O$2:O$32,"<"&'My Inputs'!$B$5)>30,"Not in 30 yrs",COUNTIF(Projection!O$2:O$32,"<"&'My Inputs'!$B$5)) -> 7 | G22: =RANK(C22,$C$9:$C$23) -> 10 | H22: =IF(C22=MAX($C$9:$C$23),C22,0) -> 0 | I22: =IF(C22=MAX($C$9:$C$23),0,C22) -> 74809.817 | J22: =A22&" "&B22 -> CIBC 1-year GIC
A23: ='Bank Products'!A19 -> CIBC | B23: ='Bank Products'!B19 -> Index fund / ETF | C23: =INDEX(Projection!P$2:P$32,'My Inputs'!$B$7+1) -> 87310.302 | D23: ='My Inputs'!$B$6+12*'My Inputs'!$B$4*'My Inputs'!$B$7 -> 62000 | E23: =C23-D23 -> 25310.302 | F23: =IF(COUNTIF(Projection!P$2:P$32,"<"&'My Inputs'!$B$5)>30,"Not in 30 yrs",COUNTIF(Projection!P$2:P$32,"<"&'My Inputs'!$B$5)) -> 6 | G23: =RANK(C23,$C$9:$C$23) -> 1 | H23: =IF(C23=MAX($C$9:$C$23),C23,0) -> 87310.302 | I23: =IF(C23=MAX($C$9:$C$23),0,C23) -> 0 | J23: =A23&" "&B23 -> CIBC Index fund / ETF
